hackerbot/__init__.py
hackerbot/core.py
hackerbot/arm/__init__.py
hackerbot/arm/gripper.py
hackerbot/base/__init__.py
hackerbot/base/maps.py
hackerbot/head/__init__.py
hackerbot/head/eyes.py
hackerbot/utils/hackerbot_helper.py
hackerbot/utils/serial_helper.py
hackerbot/utils/tts_helper.py
hackerbot-0.6.0.dist-info/licenses/LICENSE
hackerbot-0.6.0.dist-info/METADATA
hackerbot-0.6.0.dist-info/WHEEL
hackerbot-0.6.0.dist-info/top_level.txt
hackerbot-0.6.0.dist-info/RECORD
