Metadata-Version: 2.4
Name: hackerbot
Version: 0.6.0
Summary: This module contains the setup for the hackerbot python package.
Author-email: Allen Chien <allen@hackerbot.co>
License-Expression: MIT
Project-URL: Homepage, https://github.com/hackerbotindustries/hackerbot-python-package
Requires-Python: >=3.11
License-File: LICENSE
Requires-Dist: pyserial
Requires-Dist: pytest
Requires-Dist: piper-tts
Requires-Dist: sounddevice
Requires-Dist: pyaudio
Requires-Dist: huggingface_hub
Requires-Dist: requests
Dynamic: license-file
